trc.py
trc_data_reader-0.4.0.dist-info/licenses/LICENSE
trc_data_reader-0.4.0.dist-info/METADATA
trc_data_reader-0.4.0.dist-info/WHEEL
trc_data_reader-0.4.0.dist-info/top_level.txt
trc_data_reader-0.4.0.dist-info/RECORD
