Metadata-Version: 2.4
Name: trc-data-reader
Version: 0.4.0
Summary: A package for reading track row column (TRC) motion capture data.
Author-email: Hugh Sorby <h.sorby@auckland.ac.nz>
License-Expression: Apache-2.0
Project-URL: Repository, https://github.com/hsorby/trc-data-reader
Keywords: TRC,Track,Row,Column,Motion Capture
Classifier: Programming Language :: Python :: 3
Classifier: Operating System :: OS Independent
Classifier: Topic :: Scientific/Engineering :: Medical Science Apps.
Requires-Python: >=3.8
License-File: LICENSE
Requires-Dist: c3d
Provides-Extra: test
Requires-Dist: coverage; extra == "test"
Dynamic: license-file
